diamond_space/__init__.py
diamond_space/accumulator.py
diamond_space-0.0.1.dist-info/METADATA
diamond_space-0.0.1.dist-info/WHEEL
diamond_space-0.0.1.dist-info/top_level.txt
diamond_space-0.0.1.dist-info/RECORD
