Metadata-Version: 2.1
Name: diamond-space
Version: 0.0.1
Summary: Diamond space transform for python
Home-page: https://github.com/MarketaJu/diamond_space
Author: Marketa Jurankova
Author-email: jurankovam@fit.vutbr.cz
License: BSD3
Project-URL: Bug reports, https://github.com/MarketaJu/diamond_space/issues
Keywords: diamond space,pclines,hough transform,vanishing point detection,cascaded hough transform
Platform: UNKNOWN
Requires-Python: >=3.6
Requires-Dist: numpy
Requires-Dist: scikit-image
